file_mate/__init__.py
file_mate/cli.py
file_mate/converters.py
file_mate/info.py
file_mate/manipulators.py
file_mate/utils.py
file_mate/tests/test_converters.py
file_mate/tests/test_info.py
file_mate/tests/test_manipulators.py
file_mate/tests/test_utils.py
file_mate-0.1.1.dist-info/LICENSE
file_mate-0.1.1.dist-info/METADATA
file_mate-0.1.1.dist-info/WHEEL
file_mate-0.1.1.dist-info/entry_points.txt
file_mate-0.1.1.dist-info/top_level.txt
file_mate-0.1.1.dist-info/RECORD
