Metadata-Version: 2.2
Name: file-mate
Version: 0.1.1
Summary: A command-line tool for image, pdf, and other file manipulations.
Author: Anshul Gada
License: MIT
Requires-Python: >=3.8
License-File: LICENSE
Requires-Dist: Pillow
Requires-Dist: pypdf
Requires-Dist: click
Requires-Dist: reportlab
Requires-Dist: setuptools
Requires-Dist: python-magic; platform_system != "Windows"
Requires-Dist: python-magic-bin; platform_system == "Windows"
Dynamic: author
Dynamic: description
Dynamic: description-content-type
Dynamic: license
Dynamic: requires-dist
Dynamic: requires-python
Dynamic: summary
